<?xml version="1.0"?>
<?xml-stylesheet type="text/xsl" href="../entries2html.xsl" ?>
<entry type="method" name="jQuery.validator.format" returns="Function">
	<title>jQuery.validator.format()</title>
	<signature>
		<argument name="template" type="String">
			<desc>The string to format.</desc>
		</argument>
		<argument name="argument" type="Object">
			<desc>The first argument to insert, or an array of Strings to insert</desc>
		</argument>
		<argument name="argumentN..." type="Object">
			<desc>The second etc. argument to insert</desc>
		</argument>
	</signature>
	<desc>Replaces {n} placeholders with arguments.</desc>
	<longdesc>
		One or more arguments can be passed, in addition to the string template itself, to insert into the string.
		<p>If you're familiar with the term, this makes this function support currying. If you don't care about that, just use the first argument.</p>
	</longdesc>
	<example>
		<desc>Sets the debug setting for all validation calls.</desc>
		<code><![CDATA[
var template = jQuery.validator.format("{0} is not a valid value");
// later, results in 'abc is not a valid value'
alert(template("abc"));
]]></code>
	</example>
	<category slug="validator"/>
</entry>
